omnishare/__init__.py
omnishare/__main__.py
omnishare/config.py
omnishare/constants.py
omnishare/file_handler.py
omnishare/linkedin.py
omnishare/logger.py
omnishare/mastodon.py
omnishare/token_handler.py
omnishare/utils.py
omnishare-0.1.6.dist-info/LICENSE
omnishare-0.1.6.dist-info/METADATA
omnishare-0.1.6.dist-info/WHEEL
omnishare-0.1.6.dist-info/entry_points.txt
omnishare-0.1.6.dist-info/RECORD
