Metadata-Version: 2.1
Name: omnishare
Version: 0.1.6
Summary: 
Author: hyperoot
Author-email: hyperoot.tech@proton.me
Requires-Python: >=3.12,<4.0
Classifier: Programming Language :: Python :: 3
Classifier: Programming Language :: Python :: 3.12
Classifier: Programming Language :: Python :: 3.13
Requires-Dist: beaupy (>=3.9.2,<4.0.0)
Requires-Dist: cryptography (>=43.0.3,<44.0.0)
Requires-Dist: keypress (>=0.1.7,<0.2.0)
Requires-Dist: markdown-it-py (>=3.0.0,<4.0.0)
Requires-Dist: python-frontmatter (>=1.1.0,<2.0.0)
Requires-Dist: requests (>=2.32.3,<3.0.0)
Requires-Dist: rich (>=13.9.4,<14.0.0)
Requires-Dist: typer (>=0.13.1,<0.14.0)
